nttc/__init__.py
nttc/nttc.py
nttc-0.6.1.dist-info/LICENSE
nttc-0.6.1.dist-info/METADATA
nttc-0.6.1.dist-info/WHEEL
nttc-0.6.1.dist-info/top_level.txt
nttc-0.6.1.dist-info/RECORD
