Metadata-Version: 2.1
Name: nttc
Version: 0.6.1
Summary: A set of functions that process and create topic models from a sample of community-detected Twitter networks' tweets. It can process and visualize network data across periods and communities.
Home-page: https://github.com/lingeringcode/nttc/
Author: Chris A. Lindgren
Author-email: chris.a.lindgren@gmail.com
License: UNKNOWN
Download-URL: https://github.com/lingeringcode/nttc/
Keywords: data processing,topic modeling,naming network communities,network graphing
Platform: UNKNOWN
Requires-Dist: arrow
Requires-Dist: joblib
Requires-Dist: pandas
Requires-Dist: numpy
Requires-Dist: emoji
Requires-Dist: nltk
Requires-Dist: gensim
Requires-Dist: spacy
Requires-Dist: tsm
Requires-Dist: sklearn
Requires-Dist: hdbscan
Requires-Dist: seaborn
Requires-Dist: matplot
Requires-Dist: networkx
Requires-Dist: stop-words
Requires-Dist: tqdm
